<?xml version="1.0" encoding="UTF-8"?>
<groups xmlns:xsi="http://www.w3.org/2001/XMLSchema-instance" xsi:noNamespaceSchemaLocation="../schema/groups.xsd">
    <group>
        <group_id>g001</group_id>
        <group_name>Développeurs</group_name>
        <admin_id>u001</admin_id>
        <coadmins>u002</coadmins>
        <photo_groupe>devs.png</photo_groupe>
        <membre_id>u001</membre_id>
        <membre_id>u002</membre_id>
        <membre_id>u003</membre_id>
    </group>
<group><id>6880eb849d460</id><name>Groupe XML</name><id_admin>68804fa55077a</id_admin><member_id>700999888</member_id><member_id>760111222</member_id></group><group><id>6880fb6682af3</id><name>Groupe XM</name><id_admin>68804fa55077a</id_admin><member_id>700999888</member_id><member_id>760111222</member_id></group><group><id>68834a6f3be10</id><name>Groupe XML</name><id_admin>68804fa55077a</id_admin><member_id>700999888</member_id><member_id>760111222</member_id></group><group><id>68834caaa4d60</id><name>Groupe XML</name><id_admin>68804fa55077a</id_admin><group_photo>68834caaa4d6f_Capture d'écran 2025-06-15 164158.png</group_photo><member_id>700999888</member_id><member_id>760111222</member_id></group><group><group_id>g68834dd94df96</group_id><group_name>Groupe XML</group_name><admin_id>68804fa55077a</admin_id><photo_groupe>68834dd94dfa4_Capture d'écran 2025-06-15 010954.png</photo_groupe><membre_id>700999888</membre_id><membre_id>760111222</membre_id></group><group><group_id>g68834e7abdb28</group_id><group_name>Groupe XM</group_name><admin_id>68804fa55077a</admin_id><photo_groupe>68834e7abdb42_Capture d'écran 2025-06-15 162131.png</photo_groupe><membre_id>700999888</membre_id><membre_id>760111222</membre_id></group><group><group_id>g68834f2ea4dfe</group_id><group_name>Groupe XML</group_name><admin_id>68804fa55077a</admin_id><membre_id>700999888</membre_id><membre_id>760111222</membre_id></group><group><group_id>g688351db6528f</group_id><group_name>Groupe XML</group_name><admin_id>68804fa55077a</admin_id><membre_id>700999888</membre_id><membre_id>760111222</membre_id></group></groups>
